jugo/__init__.py
jugo/manage.py
jugo/data/DataObject.py
jugo/data/DataObjects.py
jugo/data/__init__.py
jugo/models/Model.py
jugo/models/__init__.py
jugo/models/types.py
jugo/utils/__init__.py
jugo/utils/connection.py
jugo/utils/exceptions.py
Jugo-1.0.7.dist-info/METADATA
Jugo-1.0.7.dist-info/WHEEL
Jugo-1.0.7.dist-info/top_level.txt
Jugo-1.0.7.dist-info/RECORD
