Metadata-Version: 2.1
Name: Jugo
Version: 1.0.7
Summary: Tool for easy communicating with MySQL/MariaDB
Home-page: https://github.com/ThreadShakur/Jugo
Author: Vadim Shpak
Author-email: lansi_bro@bk.ru
License: UNKNOWN
Platform: UNKNOWN
Classifier: Programming Language :: Python :: 3
Classifier: License :: OSI Approved :: MIT License
Classifier: Operating System :: OS Independent
Requires-Dist: pymysql
